wsgidavbcryptdc/__init__.py
wsgidavbcryptdc/controller.py
wsgidav_bcryptdc-0.1.0.dist-info/LICENSE
wsgidav_bcryptdc-0.1.0.dist-info/WHEEL
wsgidav_bcryptdc-0.1.0.dist-info/METADATA
wsgidav_bcryptdc-0.1.0.dist-info/RECORD
