Metadata-Version: 2.1
Name: wsgidav-bcryptdc
Version: 0.1.0
Summary: A simple domain controller that stores passwords as bcrypt hashes.
Keywords: wsgidav
Author-email: Andreas Bannach <andreas@borntohula.de>
Requires-Python: >=3.6
Classifier: License :: OSI Approved :: MIT License
Requires-Dist: wsgidav >=4.0
Requires-Dist: bcrypt >=4.0
Project-URL: Source, https://github.com/andban/wsgidav-bcryptdc
